sazi/__init__.py
sazi/model.py
sazi/callbacks/EarlyStopping.py
sazi/callbacks/ReduceLROnPlateau.py
sazi/callbacks/__init__.py
sazi-1.0.0.dist-info/LICENSE
sazi-1.0.0.dist-info/WHEEL
sazi-1.0.0.dist-info/METADATA
sazi-1.0.0.dist-info/RECORD
