Metadata-Version: 2.1
Name: sazi
Version: 1.0.0
Summary: This file is part of the sazi-model package.
Author-email: Sadi <toirovsadi03@gmail.com>
Classifier: License :: OSI Approved :: MIT License
